pretty_confusion_matrix/__init__.py
pretty_confusion_matrix/pretty_confusion_matrix.py
pretty_confusion_matrix-0.6.0.dist-info/LICENSE
pretty_confusion_matrix-0.6.0.dist-info/METADATA
pretty_confusion_matrix-0.6.0.dist-info/WHEEL
pretty_confusion_matrix-0.6.0.dist-info/RECORD
