Metadata-Version: 2.1
Name: pretty-confusion-matrix
Version: 0.6.0
Summary: plot a pretty confusion matrix (like Matlab) in python using seaborn and matplotlib
Home-page: https://github.com/wcipriano/pretty-print-confusion-matrix
Keywords: confusion matrix
Author: Wagner Cipriano
Author-email: wagnao@gmail.com
Requires-Python: >=3.9,<3.12
Classifier: Programming Language :: Python :: 3
Classifier: Programming Language :: Python :: 3.9
Classifier: Programming Language :: Python :: 3.10
Classifier: Programming Language :: Python :: 3.11
Requires-Dist: matplotlib (>=3.9.0,<4.0.0) ; python_version >= "3.9"
Requires-Dist: numpy (>=2.0.0,<3.0.0) ; python_version >= "3.9"
Requires-Dist: pandas (>=2.2.2,<3.0.0) ; python_version >= "3.9"
Requires-Dist: scikit-learn (>=1.5,<2.0) ; python_version >= "3.9"
Requires-Dist: seaborn (>=0.13.2,<0.14.0)
Project-URL: Repository, https://github.com/wcipriano/pretty-print-confusion-matrix
